__init__.py
date.py
dateFormat.py
filename.py
functionality.py
genericElement.py
logParser.py
severity.py
PyLogParser-0.0.1.data/data/LICENSE
PyLogParser-0.0.1.data/data/README.md
PyLogParser-0.0.1.dist-info/LICENSE
PyLogParser-0.0.1.dist-info/METADATA
PyLogParser-0.0.1.dist-info/WHEEL
PyLogParser-0.0.1.dist-info/entry_points.txt
PyLogParser-0.0.1.dist-info/top_level.txt
PyLogParser-0.0.1.dist-info/RECORD
